openid_connect/__init__.py
openid_connect/_connect.py
openid_connect/_netloc.py
openid_connect/_oidc.py
openid_connect/_property.py
openid_connect/_request_auth.py
openid_connect/_verify.py
openid_connect/errors.py
openid_connect/op.py
openid_connect/rp.py
openid_connect/legacy/__init__.py
openid_connect/legacy/_oauth2.py
openid_connect/legacy/_util.py
openid_connect/legacy/facebook.py
openid_connect/legacy/github.py
openid_connect/legacy/gitlab.py
openid_connect-0.5.0.dist-info/LICENSE
openid_connect-0.5.0.dist-info/LICENSE.BSD
openid_connect-0.5.0.dist-info/METADATA
openid_connect-0.5.0.dist-info/WHEEL
openid_connect-0.5.0.dist-info/top_level.txt
openid_connect-0.5.0.dist-info/zip-safe
openid_connect-0.5.0.dist-info/RECORD
