Metadata-Version: 2.1
Name: openid-connect
Version: 0.5.0
Summary: Low-level Python OIDC Client library
Home-page: https://gitlab.com/aiakos/python-openid-connect
Author: Aiakos Contributors
Author-email: aiakos@aiakosauth.com
License: MIT
Keywords: auth oauth openid oidc social ldap
Platform: UNKNOWN
Classifier: Development Status :: 5 - Production/Stable
Classifier: Intended Audience :: System Administrators
Classifier: License :: OSI Approved :: MIT License
Classifier: License :: OSI Approved :: BSD License
Classifier: Programming Language :: Python
Classifier: Programming Language :: Python :: 3
Classifier: Programming Language :: Python :: 3.7
Classifier: Topic :: System :: Systems Administration :: Authentication/Directory
Requires-Dist: python-jose
Requires-Dist: requests
